graphene_pydantic_updated/__init__.py
graphene_pydantic_updated/converters.py
graphene_pydantic_updated/inputobjecttype.py
graphene_pydantic_updated/objecttype.py
graphene_pydantic_updated/registry.py
graphene_pydantic_updated/util.py
graphene_pydantic_updated-0.1.0.dist-info/WHEEL
graphene_pydantic_updated-0.1.0.dist-info/METADATA
graphene_pydantic_updated-0.1.0.dist-info/RECORD
